hanzo_tools/__init__.py
hanzo_tools/refactor/__init__.py
hanzo_tools/refactor/refactor_tool.py
hanzo_tools_refactor-0.2.0.dist-info/METADATA
hanzo_tools_refactor-0.2.0.dist-info/WHEEL
hanzo_tools_refactor-0.2.0.dist-info/entry_points.txt
hanzo_tools_refactor-0.2.0.dist-info/top_level.txt
hanzo_tools_refactor-0.2.0.dist-info/RECORD
