Metadata-Version: 2.4
Name: hanzo-tools-refactor
Version: 0.2.0
Summary: Refactoring tools for Hanzo AI - rename, extract, inline, move with LSP/AST
Author-email: Hanzo Industries Inc <dev@hanzo.ai>
License: MIT
Project-URL: Homepage, https://github.com/hanzoai/python-sdk
Keywords: hanzo,tools,refactor,lsp,ast,mcp,ai
Classifier: Programming Language :: Python :: 3
Classifier: License :: OSI Approved :: MIT License
Classifier: Operating System :: OS Independent
Requires-Python: >=3.12
Requires-Dist: hanzo-tools-core>=0.1.0
Requires-Dist: mcp>=1.25.0
Requires-Dist: fastmcp>=2.14.1
Requires-Dist: pydantic>=2.12.5
Provides-Extra: full
Requires-Dist: tree-sitter>=0.24.0; extra == "full"
Requires-Dist: tree-sitter-python>=0.23.6; extra == "full"
Requires-Dist: tree-sitter-javascript>=0.23.1; extra == "full"
Requires-Dist: tree-sitter-typescript>=0.23.2; extra == "full"
Requires-Dist: tree-sitter-go>=0.23.4; extra == "full"
Requires-Dist: tree-sitter-rust>=0.23.2; extra == "full"
Provides-Extra: dev
Requires-Dist: pytest>=7.0.0; extra == "dev"
Requires-Dist: ruff>=0.14.0; extra == "dev"
